cga_py/__init__.py
cga_py/base_objects.py
cga_py/conditions.py
cga_py/dorst_motions.py
cga_py/errors.py
cga_py/four_quaternions.py
cga_py/geom_generators.py
cga_py/kinematic_polynomials.py
cga_py/multivector.py
cga_py/operators.py
cga_py/permutations.py
cga_py/permutations_pm.py
cga_py/random.py
cga_py/random_gen.py
cga_py/visualization.py
cga_py-1.3.3.dist-info/licenses/LICENSE
cga_py-1.3.3.dist-info/METADATA
cga_py-1.3.3.dist-info/WHEEL
cga_py-1.3.3.dist-info/entry_points.txt
cga_py-1.3.3.dist-info/top_level.txt
cga_py-1.3.3.dist-info/RECORD
