Metadata-Version: 2.4
Name: cga-py
Version: 1.3.3
Summary: Implementation of CGA for python
Author-email: Daren Thimm <daren.thimm@gmx.at>
Maintainer-email: Daren Thimm <daren.thimm@gmx.at>
License: BSD 3-Clause License
Project-URL: Source, https://github.com/physicspenguin/cga-py
Classifier: License :: OSI Approved :: BSD License
Classifier: Natural Language :: English
Classifier: Operating System :: OS Independent
Classifier: Programming Language :: Python
Requires-Python: >=3.10
License-File: LICENSE
Requires-Dist: setuptools>=80.9.0
Requires-Dist: numba>=0.61.2
Requires-Dist: numpy>=1.21
Requires-Dist: pyqtgraph>=0.13.7
Requires-Dist: PyQt5>=5.15.11
Requires-Dist: PyQt6>=6.9.1
Requires-Dist: PyOpenGL>=3.1.10
Provides-Extra: doc
Requires-Dist: sphinx~=8.2.3; extra == "doc"
Requires-Dist: myst-parser; extra == "doc"
Requires-Dist: sphinx-rtd-theme; extra == "doc"
Requires-Dist: nbsphinx; extra == "doc"
Requires-Dist: numpydoc; extra == "doc"
Provides-Extra: dev
Requires-Dist: flake8==7.3.0; extra == "dev"
Requires-Dist: pytest==8.4.1; extra == "dev"
Requires-Dist: pytest-cov==6.2.1; extra == "dev"
Requires-Dist: pre-commit==4.3.0; extra == "dev"
Requires-Dist: tox==4.28.4; extra == "dev"
Provides-Extra: publish
Requires-Dist: twine>=6.1.0; extra == "publish"
Requires-Dist: build>=1.3.0; extra == "publish"
Dynamic: license-file
